{
  "$schema": "http://json-schema.org/draft-04/schema#",
  "type": "object",
  "properties": {
    "$schema": {
      "type": "string"
    },
    "type": {
      "type": "string"
    },
    "properties": {
      "type": "object",
      "properties": {
        "action.<action_name>": {
          "type": "object",
          "properties": {
            "type": {
              "type": "string"
            }
          },
          "required": [
            "type"
          ]
        },
        "action.<action_name>.<parameter>": {
          "type": "object",
          "properties": {
            "type": {
              "type": "string"
            }
          },
          "required": [
            "type"
          ]
        },
        "action.email": {
          "type": "object",
          "properties": {
            "type": {
              "type": "string"
            }
          },
          "required": [
            "type"
          ]
        },
        "action.email.auth_password": {
          "type": "object",
          "properties": {
            "type": {
              "type": "string"
            }
          },
          "required": [
            "type"
          ]
        },
        "action.email.auth_username": {
          "type": "object",
          "properties": {
            "type": {
              "type": "string"
            }
          },
          "required": [
            "type"
          ]
        },
        "action.email.bcc": {
          "type": "object",
          "properties": {
            "type": {
              "type": "string"
            }
          },
          "required": [
            "type"
          ]
        },
        "action.email.cc": {
          "type": "object",
          "properties": {
            "type": {
              "type": "string"
            }
          },
          "required": [
            "type"
          ]
        },
        "action.email.command": {
          "type": "object",
          "properties": {
            "type": {
              "type": "string"
            }
          },
          "required": [
            "type"
          ]
        },
        "action.email.format": {
          "type": "object",
          "properties": {
            "type": {
              "type": "string"
            }
          },
          "required": [
            "type"
          ]
        },
        "action.email.from": {
          "type": "object",
          "properties": {
            "type": {
              "type": "string"
            }
          },
          "required": [
            "type"
          ]
        },
        "action.email.hostname": {
          "type": "object",
          "properties": {
            "type": {
              "type": "string"
            }
          },
          "required": [
            "type"
          ]
        },
        "action.email.inline": {
          "type": "object",
          "properties": {
            "type": {
              "type": "string"
            }
          },
          "required": [
            "type"
          ]
        },
        "action.email.mailserver": {
          "type": "object",
          "properties": {
            "type": {
              "type": "string"
            }
          },
          "required": [
            "type"
          ]
        },
        "action.email.maxresults": {
          "type": "object",
          "properties": {
            "type": {
              "type": "string"
            }
          },
          "required": [
            "type"
          ]
        },
        "action.email.maxtime": {
          "type": "object",
          "properties": {
            "type": {
              "type": "string"
            }
          },
          "required": [
            "type"
          ]
        },
        "action.email.pdfview": {
          "type": "object",
          "properties": {
            "type": {
              "type": "string"
            }
          },
          "required": [
            "type"
          ]
        },
        "action.email.preprocess_results": {
          "type": "object",
          "properties": {
            "type": {
              "type": "string"
            }
          },
          "required": [
            "type"
          ]
        },
        "action.email.reportCIDFontList": {
          "type": "object",
          "properties": {
            "type": {
              "type": "string"
            }
          },
          "required": [
            "type"
          ]
        },
        "action.email.reportIncludeSplunkLogo": {
          "type": "object",
          "properties": {
            "type": {
              "type": "string"
            }
          },
          "required": [
            "type"
          ]
        },
        "action.email.reportPaperOrientation": {
          "type": "object",
          "properties": {
            "type": {
              "type": "string"
            }
          },
          "required": [
            "type"
          ]
        },
        "action.email.reportPaperSize": {
          "type": "object",
          "properties": {
            "type": {
              "type": "string"
            }
          },
          "required": [
            "type"
          ]
        },
        "action.email.reportServerEnabled": {
          "type": "object",
          "properties": {
            "type": {
              "type": "string"
            }
          },
          "required": [
            "type"
          ]
        },
        "action.email.reportServerURL": {
          "type": "object",
          "properties": {
            "type": {
              "type": "string"
            }
          },
          "required": [
            "type"
          ]
        },
        "action.email.sendpdf": {
          "type": "object",
          "properties": {
            "type": {
              "type": "string"
            }
          },
          "required": [
            "type"
          ]
        },
        "action.email.sendresults": {
          "type": "object",
          "properties": {
            "type": {
              "type": "string"
            }
          },
          "required": [
            "type"
          ]
        },
        "action.email.subject": {
          "type": "object",
          "properties": {
            "type": {
              "type": "string"
            }
          },
          "required": [
            "type"
          ]
        },
        "action.email.to": {
          "type": "object",
          "properties": {
            "type": {
              "type": "string"
            }
          },
          "required": [
            "type"
          ]
        },
        "action.email.track_alert": {
          "type": "object",
          "properties": {
            "type": {
              "type": "string"
            }
          },
          "required": [
            "type"
          ]
        },
        "action.email.ttl": {
          "type": "object",
          "properties": {
            "type": {
              "type": "string"
            }
          },
          "required": [
            "type"
          ]
        },
        "action.email.use_ssl": {
          "type": "object",
          "properties": {
            "type": {
              "type": "string"
            }
          },
          "required": [
            "type"
          ]
        },
        "action.email.use_tls": {
          "type": "object",
          "properties": {
            "type": {
              "type": "string"
            }
          },
          "required": [
            "type"
          ]
        },
        "action.email.width_sort_columns": {
          "type": "object",
          "properties": {
            "type": {
              "type": "string"
            }
          },
          "required": [
            "type"
          ]
        },
        "action.populate_lookup": {
          "type": "object",
          "properties": {
            "type": {
              "type": "string"
            }
          },
          "required": [
            "type"
          ]
        },
        "action.populate_lookup.command": {
          "type": "object",
          "properties": {
            "type": {
              "type": "string"
            }
          },
          "required": [
            "type"
          ]
        },
        "action.populate_lookup.dest": {
          "type": "object",
          "properties": {
            "type": {
              "type": "string"
            }
          },
          "required": [
            "type"
          ]
        },
        "action.populate_lookup.hostname": {
          "type": "object",
          "properties": {
            "type": {
              "type": "string"
            }
          },
          "required": [
            "type"
          ]
        },
        "action.populate_lookup.maxresults": {
          "type": "object",
          "properties": {
            "type": {
              "type": "string"
            }
          },
          "required": [
            "type"
          ]
        },
        "action.populate_lookup.maxtime": {
          "type": "object",
          "properties": {
            "type": {
              "type": "string"
            }
          },
          "required": [
            "type"
          ]
        },
        "action.populate_lookup.track_alert": {
          "type": "object",
          "properties": {
            "type": {
              "type": "string"
            }
          },
          "required": [
            "type"
          ]
        },
        "action.populate_lookup.ttl": {
          "type": "object",
          "properties": {
            "type": {
              "type": "string"
            }
          },
          "required": [
            "type"
          ]
        },
        "action.rss": {
          "type": "object",
          "properties": {
            "type": {
              "type": "string"
            }
          },
          "required": [
            "type"
          ]
        },
        "action.rss.command": {
          "type": "object",
          "properties": {
            "type": {
              "type": "string"
            }
          },
          "required": [
            "type"
          ]
        },
        "action.rss.hostname": {
          "type": "object",
          "properties": {
            "type": {
              "type": "string"
            }
          },
          "required": [
            "type"
          ]
        },
        "action.rss.maxresults": {
          "type": "object",
          "properties": {
            "type": {
              "type": "string"
            }
          },
          "required": [
            "type"
          ]
        },
        "action.rss.maxtime": {
          "type": "object",
          "properties": {
            "type": {
              "type": "string"
            }
          },
          "required": [
            "type"
          ]
        },
        "action.rss.track_alert": {
          "type": "object",
          "properties": {
            "type": {
              "type": "string"
            }
          },
          "required": [
            "type"
          ]
        },
        "action.rss.ttl": {
          "type": "object",
          "properties": {
            "type": {
              "type": "string"
            }
          },
          "required": [
            "type"
          ]
        },
        "action.script": {
          "type": "object",
          "properties": {
            "type": {
              "type": "string"
            }
          },
          "required": [
            "type"
          ]
        },
        "action.script.command": {
          "type": "object",
          "properties": {
            "type": {
              "type": "string"
            }
          },
          "required": [
            "type"
          ]
        },
        "action.script.filename": {
          "type": "object",
          "properties": {
            "type": {
              "type": "string"
            }
          },
          "required": [
            "type"
          ]
        },
        "action.script.hostname": {
          "type": "object",
          "properties": {
            "type": {
              "type": "string"
            }
          },
          "required": [
            "type"
          ]
        },
        "action.script.maxresults": {
          "type": "object",
          "properties": {
            "type": {
              "type": "string"
            }
          },
          "required": [
            "type"
          ]
        },
        "action.script.maxtime": {
          "type": "object",
          "properties": {
            "type": {
              "type": "string"
            }
          },
          "required": [
            "type"
          ]
        },
        "action.script.track_alert": {
          "type": "object",
          "properties": {
            "type": {
              "type": "string"
            }
          },
          "required": [
            "type"
          ]
        },
        "action.script.ttl": {
          "type": "object",
          "properties": {
            "type": {
              "type": "string"
            }
          },
          "required": [
            "type"
          ]
        },
        "action.summary_index": {
          "type": "object",
          "properties": {
            "type": {
              "type": "string"
            }
          },
          "required": [
            "type"
          ]
        },
        "action.summary_index._name": {
          "type": "object",
          "properties": {
            "type": {
              "type": "string"
            }
          },
          "required": [
            "type"
          ]
        },
        "action.summary_index.command": {
          "type": "object",
          "properties": {
            "type": {
              "type": "string"
            }
          },
          "required": [
            "type"
          ]
        },
        "action.summary_index.hostname": {
          "type": "object",
          "properties": {
            "type": {
              "type": "string"
            }
          },
          "required": [
            "type"
          ]
        },
        "action.summary_index.inline": {
          "type": "object",
          "properties": {
            "type": {
              "type": "string"
            }
          },
          "required": [
            "type"
          ]
        },
        "action.summary_index.maxresults": {
          "type": "object",
          "properties": {
            "type": {
              "type": "string"
            }
          },
          "required": [
            "type"
          ]
        },
        "action.summary_index.maxtime": {
          "type": "object",
          "properties": {
            "type": {
              "type": "string"
            }
          },
          "required": [
            "type"
          ]
        },
        "action.summary_index.track_alert": {
          "type": "object",
          "properties": {
            "type": {
              "type": "string"
            }
          },
          "required": [
            "type"
          ]
        },
        "action.summary_index.ttl": {
          "type": "object",
          "properties": {
            "type": {
              "type": "string"
            }
          },
          "required": [
            "type"
          ]
        },
        "actions": {
          "type": "object",
          "properties": {
            "type": {
              "type": "string"
            }
          },
          "required": [
            "type"
          ]
        },
        "alert.digest_mode": {
          "type": "object",
          "properties": {
            "type": {
              "type": "string"
            }
          },
          "required": [
            "type"
          ]
        },
        "alert.expires": {
          "type": "object",
          "properties": {
            "type": {
              "type": "string"
            }
          },
          "required": [
            "type"
          ]
        },
        "alert.severity": {
          "type": "object",
          "properties": {
            "type": {
              "type": "string"
            }
          },
          "required": [
            "type"
          ]
        },
        "alert.suppress": {
          "type": "object",
          "properties": {
            "type": {
              "type": "string"
            }
          },
          "required": [
            "type"
          ]
        },
        "alert.suppress.fields": {
          "type": "object",
          "properties": {
            "type": {
              "type": "string"
            }
          },
          "required": [
            "type"
          ]
        },
        "alert.suppress.period": {
          "type": "object",
          "properties": {
            "type": {
              "type": "string"
            }
          },
          "required": [
            "type"
          ]
        },
        "alert.track": {
          "type": "object",
          "properties": {
            "type": {
              "type": "string"
            }
          },
          "required": [
            "type"
          ]
        },
        "alert_comparator": {
          "type": "object",
          "properties": {
            "type": {
              "type": "string"
            }
          },
          "required": [
            "type"
          ]
        },
        "alert_condition": {
          "type": "object",
          "properties": {
            "type": {
              "type": "string"
            }
          },
          "required": [
            "type"
          ]
        },
        "alert_threshold": {
          "type": "object",
          "properties": {
            "type": {
              "type": "string"
            }
          },
          "required": [
            "type"
          ]
        },
        "alert_type": {
          "type": "object",
          "properties": {
            "type": {
              "type": "string"
            }
          },
          "required": [
            "type"
          ]
        },
        "allow_skew": {
          "type": "object",
          "properties": {
            "type": {
              "type": "string"
            }
          },
          "required": [
            "type"
          ]
        },
        "args.*": {
          "type": "object",
          "properties": {
            "type": {
              "type": "string"
            }
          },
          "required": [
            "type"
          ]
        },
        "auto_summarize": {
          "type": "object",
          "properties": {
            "type": {
              "type": "string"
            }
          },
          "required": [
            "type"
          ]
        },
        "auto_summarize.command": {
          "type": "object",
          "properties": {
            "type": {
              "type": "string"
            }
          },
          "required": [
            "type"
          ]
        },
        "auto_summarize.cron_schedule": {
          "type": "object",
          "properties": {
            "type": {
              "type": "string"
            }
          },
          "required": [
            "type"
          ]
        },
        "auto_summarize.dispatch.earliest_time": {
          "type": "object",
          "properties": {
            "type": {
              "type": "string"
            }
          },
          "required": [
            "type"
          ]
        },
        "auto_summarize.dispatch.latest_time": {
          "type": "object",
          "properties": {
            "type": {
              "type": "string"
            }
          },
          "required": [
            "type"
          ]
        },
        "auto_summarize.dispatch.time_format": {
          "type": "object",
          "properties": {
            "type": {
              "type": "string"
            }
          },
          "required": [
            "type"
          ]
        },
        "auto_summarize.dispatch.ttl": {
          "type": "object",
          "properties": {
            "type": {
              "type": "string"
            }
          },
          "required": [
            "type"
          ]
        },
        "auto_summarize.max_disabled_buckets": {
          "type": "object",
          "properties": {
            "type": {
              "type": "string"
            }
          },
          "required": [
            "type"
          ]
        },
        "auto_summarize.max_summary_ratio": {
          "type": "object",
          "properties": {
            "type": {
              "type": "string"
            }
          },
          "required": [
            "type"
          ]
        },
        "auto_summarize.max_summary_size": {
          "type": "object",
          "properties": {
            "type": {
              "type": "string"
            }
          },
          "required": [
            "type"
          ]
        },
        "auto_summarize.max_time": {
          "type": "object",
          "properties": {
            "type": {
              "type": "string"
            }
          },
          "required": [
            "type"
          ]
        },
        "auto_summarize.suspend_period": {
          "type": "object",
          "properties": {
            "type": {
              "type": "string"
            }
          },
          "required": [
            "type"
          ]
        },
        "auto_summarize.timespan": {
          "type": "object",
          "properties": {
            "type": {
              "type": "string"
            }
          },
          "required": [
            "type"
          ]
        },
        "cron_schedule": {
          "type": "object",
          "properties": {
            "type": {
              "type": "string"
            }
          },
          "required": [
            "type"
          ]
        },
        "description": {
          "type": "object",
          "properties": {
            "type": {
              "type": "string"
            }
          },
          "required": [
            "type"
          ]
        },
        "disabled": {
          "type": "object",
          "properties": {
            "type": {
              "type": "string"
            }
          },
          "required": [
            "type"
          ]
        },
        "dispatch.*": {
          "type": "object",
          "properties": {
            "type": {
              "type": "string"
            }
          },
          "required": [
            "type"
          ]
        },
        "dispatch.buckets": {
          "type": "object",
          "properties": {
            "type": {
              "type": "string"
            }
          },
          "required": [
            "type"
          ]
        },
        "dispatch.earliest_time": {
          "type": "object",
          "properties": {
            "type": {
              "type": "string"
            }
          },
          "required": [
            "type"
          ]
        },
        "dispatch.indexedRealtime": {
          "type": "object",
          "properties": {
            "type": {
              "type": "string"
            }
          },
          "required": [
            "type"
          ]
        },
        "dispatch.indexedRealtimeOffset": {
          "type": "object",
          "properties": {
            "type": {
              "type": "string"
            }
          },
          "required": [
            "type"
          ]
        },
        "dispatch.indexedRealtimeMinSpan": {
          "type": "object",
          "properties": {
            "type": {
              "type": "string"
            }
          },
          "required": [
            "type"
          ]
        },
        "dispatch.latest_time": {
          "type": "object",
          "properties": {
            "type": {
              "type": "string"
            }
          },
          "required": [
            "type"
          ]
        },
        "dispatch.lookups": {
          "type": "object",
          "properties": {
            "type": {
              "type": "string"
            }
          },
          "required": [
            "type"
          ]
        },
        "dispatch.max_count": {
          "type": "object",
          "properties": {
            "type": {
              "type": "string"
            }
          },
          "required": [
            "type"
          ]
        },
        "dispatch.max_time": {
          "type": "object",
          "properties": {
            "type": {
              "type": "string"
            }
          },
          "required": [
            "type"
          ]
        },
        "dispatch.reduce_freq": {
          "type": "object",
          "properties": {
            "type": {
              "type": "string"
            }
          },
          "required": [
            "type"
          ]
        },
        "dispatch.rt_backfill": {
          "type": "object",
          "properties": {
            "type": {
              "type": "string"
            }
          },
          "required": [
            "type"
          ]
        },
        "dispatch.rt_maximum_span": {
          "type": "object",
          "properties": {
            "type": {
              "type": "string"
            }
          },
          "required": [
            "type"
          ]
        },
        "dispatch.spawn_process": {
          "type": "object",
          "properties": {
            "type": {
              "type": "string"
            }
          },
          "required": [
            "type"
          ]
        },
        "dispatch.time_format": {
          "type": "object",
          "properties": {
            "type": {
              "type": "string"
            }
          },
          "required": [
            "type"
          ]
        },
        "dispatch.ttl": {
          "type": "object",
          "properties": {
            "type": {
              "type": "string"
            }
          },
          "required": [
            "type"
          ]
        },
        "displayview": {
          "type": "object",
          "properties": {
            "type": {
              "type": "string"
            }
          },
          "required": [
            "type"
          ]
        },
        "is_scheduled": {
          "type": "object",
          "properties": {
            "type": {
              "type": "string"
            }
          },
          "required": [
            "type"
          ]
        },
        "is_visible": {
          "type": "object",
          "properties": {
            "type": {
              "type": "string"
            }
          },
          "required": [
            "type"
          ]
        },
        "max_concurrent": {
          "type": "object",
          "properties": {
            "type": {
              "type": "string"
            }
          },
          "required": [
            "type"
          ]
        },
        "name": {
          "type": "object",
          "properties": {
            "type": {
              "type": "string"
            }
          },
          "required": [
            "type"
          ]
        },
        "next_scheduled_time": {
          "type": "object",
          "properties": {
            "type": {
              "type": "string"
            }
          },
          "required": [
            "type"
          ]
        },
        "qualifiedSearch": {
          "type": "object",
          "properties": {
            "type": {
              "type": "string"
            }
          },
          "required": [
            "type"
          ]
        },
        "realtime_schedule": {
          "type": "object",
          "properties": {
            "type": {
              "type": "string"
            }
          },
          "required": [
            "type"
          ]
        },
        "request.ui_dispatch_app": {
          "type": "object",
          "properties": {
            "type": {
              "type": "string"
            }
          },
          "required": [
            "type"
          ]
        },
        "request.ui_dispatch_view": {
          "type": "object",
          "properties": {
            "type": {
              "type": "string"
            }
          },
          "required": [
            "type"
          ]
        },
        "restart_on_searchpeer_add": {
          "type": "object",
          "properties": {
            "type": {
              "type": "string"
            }
          },
          "required": [
            "type"
          ]
        },
        "run_on_startup": {
          "type": "object",
          "properties": {
            "type": {
              "type": "string"
            }
          },
          "required": [
            "type"
          ]
        },
        "schedule_window": {
          "type": "object",
          "properties": {
            "type": {
              "type": "string"
            }
          },
          "required": [
            "type"
          ]
        },
        "search": {
          "type": "object",
          "properties": {
            "type": {
              "type": "string"
            }
          },
          "required": [
            "type"
          ]
        },
        "schedule_priority": {
          "type": "object",
          "properties": {
            "type": {
              "type": "string"
            }
          },
          "required": [
            "type"
          ]
        },
        "vsid": {
          "type": "object",
          "properties": {
            "type": {
              "type": "string"
            }
          },
          "required": [
            "type"
          ]
        },
        "workload_pool": {
          "type": "object",
          "properties": {
            "type": {
              "type": "string"
            }
          },
          "required": [
            "type"
          ]
        }
      },
      "required": [
        "action.<action_name>",
        "action.<action_name>.<parameter>",
        "action.email",
        "action.email.auth_password",
        "action.email.auth_username",
        "action.email.bcc",
        "action.email.cc",
        "action.email.command",
        "action.email.format",
        "action.email.from",
        "action.email.hostname",
        "action.email.inline",
        "action.email.mailserver",
        "action.email.maxresults",
        "action.email.maxtime",
        "action.email.pdfview",
        "action.email.preprocess_results",
        "action.email.reportCIDFontList",
        "action.email.reportIncludeSplunkLogo",
        "action.email.reportPaperOrientation",
        "action.email.reportPaperSize",
        "action.email.reportServerEnabled",
        "action.email.reportServerURL",
        "action.email.sendpdf",
        "action.email.sendresults",
        "action.email.subject",
        "action.email.to",
        "action.email.track_alert",
        "action.email.ttl",
        "action.email.use_ssl",
        "action.email.use_tls",
        "action.email.width_sort_columns",
        "action.populate_lookup",
        "action.populate_lookup.command",
        "action.populate_lookup.dest",
        "action.populate_lookup.hostname",
        "action.populate_lookup.maxresults",
        "action.populate_lookup.maxtime",
        "action.populate_lookup.track_alert",
        "action.populate_lookup.ttl",
        "action.rss",
        "action.rss.command",
        "action.rss.hostname",
        "action.rss.maxresults",
        "action.rss.maxtime",
        "action.rss.track_alert",
        "action.rss.ttl",
        "action.script",
        "action.script.command",
        "action.script.filename",
        "action.script.hostname",
        "action.script.maxresults",
        "action.script.maxtime",
        "action.script.track_alert",
        "action.script.ttl",
        "action.summary_index",
        "action.summary_index._name",
        "action.summary_index.command",
        "action.summary_index.hostname",
        "action.summary_index.inline",
        "action.summary_index.maxresults",
        "action.summary_index.maxtime",
        "action.summary_index.track_alert",
        "action.summary_index.ttl",
        "actions",
        "alert.digest_mode",
        "alert.expires",
        "alert.severity",
        "alert.suppress",
        "alert.suppress.fields",
        "alert.suppress.period",
        "alert.track",
        "alert_comparator",
        "alert_condition",
        "alert_threshold",
        "alert_type",
        "allow_skew",
        "args.*",
        "auto_summarize",
        "auto_summarize.command",
        "auto_summarize.cron_schedule",
        "auto_summarize.dispatch.earliest_time",
        "auto_summarize.dispatch.latest_time",
        "auto_summarize.dispatch.time_format",
        "auto_summarize.dispatch.ttl",
        "auto_summarize.max_disabled_buckets",
        "auto_summarize.max_summary_ratio",
        "auto_summarize.max_summary_size",
        "auto_summarize.max_time",
        "auto_summarize.suspend_period",
        "auto_summarize.timespan",
        "cron_schedule",
        "description",
        "disabled",
        "dispatch.*",
        "dispatch.buckets",
        "dispatch.earliest_time",
        "dispatch.indexedRealtime",
        "dispatch.indexedRealtimeOffset",
        "dispatch.indexedRealtimeMinSpan",
        "dispatch.latest_time",
        "dispatch.lookups",
        "dispatch.max_count",
        "dispatch.max_time",
        "dispatch.reduce_freq",
        "dispatch.rt_backfill",
        "dispatch.rt_maximum_span",
        "dispatch.spawn_process",
        "dispatch.time_format",
        "dispatch.ttl",
        "displayview",
        "is_scheduled",
        "is_visible",
        "max_concurrent",
        "name",
        "next_scheduled_time",
        "qualifiedSearch",
        "realtime_schedule",
        "request.ui_dispatch_app",
        "request.ui_dispatch_view",
        "restart_on_searchpeer_add",
        "run_on_startup",
        "schedule_window",
        "search",
        "schedule_priority",
        "vsid",
        "workload_pool"
      ]
    },
    "required": {
      "type": "array",
      "items": [
        {
          "type": "string"
        },
        {
          "type": "string"
        },
        {
          "type": "string"
        },
        {
          "type": "string"
        },
        {
          "type": "string"
        },
        {
          "type": "string"
        },
        {
          "type": "string"
        },
        {
          "type": "string"
        },
        {
          "type": "string"
        },
        {
          "type": "string"
        },
        {
          "type": "string"
        },
        {
          "type": "string"
        },
        {
          "type": "string"
        },
        {
          "type": "string"
        },
        {
          "type": "string"
        },
        {
          "type": "string"
        },
        {
          "type": "string"
        },
        {
          "type": "string"
        },
        {
          "type": "string"
        },
        {
          "type": "string"
        },
        {
          "type": "string"
        },
        {
          "type": "string"
        },
        {
          "type": "string"
        },
        {
          "type": "string"
        },
        {
          "type": "string"
        },
        {
          "type": "string"
        },
        {
          "type": "string"
        },
        {
          "type": "string"
        },
        {
          "type": "string"
        },
        {
          "type": "string"
        },
        {
          "type": "string"
        },
        {
          "type": "string"
        },
        {
          "type": "string"
        },
        {
          "type": "string"
        },
        {
          "type": "string"
        },
        {
          "type": "string"
        },
        {
          "type": "string"
        },
        {
          "type": "string"
        },
        {
          "type": "string"
        },
        {
          "type": "string"
        },
        {
          "type": "string"
        },
        {
          "type": "string"
        },
        {
          "type": "string"
        },
        {
          "type": "string"
        },
        {
          "type": "string"
        },
        {
          "type": "string"
        },
        {
          "type": "string"
        },
        {
          "type": "string"
        },
        {
          "type": "string"
        },
        {
          "type": "string"
        },
        {
          "type": "string"
        },
        {
          "type": "string"
        },
        {
          "type": "string"
        },
        {
          "type": "string"
        },
        {
          "type": "string"
        },
        {
          "type": "string"
        },
        {
          "type": "string"
        },
        {
          "type": "string"
        },
        {
          "type": "string"
        },
        {
          "type": "string"
        },
        {
          "type": "string"
        },
        {
          "type": "string"
        },
        {
          "type": "string"
        },
        {
          "type": "string"
        },
        {
          "type": "string"
        },
        {
          "type": "string"
        },
        {
          "type": "string"
        },
        {
          "type": "string"
        },
        {
          "type": "string"
        },
        {
          "type": "string"
        },
        {
          "type": "string"
        },
        {
          "type": "string"
        },
        {
          "type": "string"
        },
        {
          "type": "string"
        },
        {
          "type": "string"
        },
        {
          "type": "string"
        },
        {
          "type": "string"
        },
        {
          "type": "string"
        },
        {
          "type": "string"
        },
        {
          "type": "string"
        },
        {
          "type": "string"
        },
        {
          "type": "string"
        },
        {
          "type": "string"
        },
        {
          "type": "string"
        },
        {
          "type": "string"
        },
        {
          "type": "string"
        },
        {
          "type": "string"
        },
        {
          "type": "string"
        },
        {
          "type": "string"
        },
        {
          "type": "string"
        },
        {
          "type": "string"
        },
        {
          "type": "string"
        },
        {
          "type": "string"
        },
        {
          "type": "string"
        },
        {
          "type": "string"
        },
        {
          "type": "string"
        },
        {
          "type": "string"
        },
        {
          "type": "string"
        },
        {
          "type": "string"
        },
        {
          "type": "string"
        },
        {
          "type": "string"
        },
        {
          "type": "string"
        },
        {
          "type": "string"
        },
        {
          "type": "string"
        },
        {
          "type": "string"
        },
        {
          "type": "string"
        },
        {
          "type": "string"
        },
        {
          "type": "string"
        },
        {
          "type": "string"
        },
        {
          "type": "string"
        },
        {
          "type": "string"
        },
        {
          "type": "string"
        },
        {
          "type": "string"
        },
        {
          "type": "string"
        },
        {
          "type": "string"
        },
        {
          "type": "string"
        },
        {
          "type": "string"
        },
        {
          "type": "string"
        },
        {
          "type": "string"
        },
        {
          "type": "string"
        },
        {
          "type": "string"
        },
        {
          "type": "string"
        },
        {
          "type": "string"
        },
        {
          "type": "string"
        },
        {
          "type": "string"
        },
        {
          "type": "string"
        },
        {
          "type": "string"
        }
      ]
    }
  },
  "required": [
    "$schema",
    "type",
    "properties",
    "required"
  ]
}